VISualMAth-1.0.0.0.data/scripts/visma
tests/__init__.py
tests/test_calculus.py
tests/test_discrete.py
tests/test_functions.py
tests/test_io.py
tests/test_matrix.py
tests/test_simplify.py
tests/test_solvers.py
tests/test_transform.py
tests/test_utils.py
tests/tester.py
visma/__init__.py
visma/main.py
visma/calculus/__init__.py
visma/calculus/differentiation.py
visma/calculus/integration.py
visma/config/__init__.py
visma/config/values.py
visma/discreteMaths/__init__.py
visma/discreteMaths/boolean.py
visma/discreteMaths/combinatorics.py
visma/discreteMaths/probability.py
visma/discreteMaths/statistics.py
visma/functions/__init__.py
visma/functions/constant.py
visma/functions/exponential.py
visma/functions/hyperbolic.py
visma/functions/operator.py
visma/functions/structure.py
visma/functions/trigonometry.py
visma/functions/variable.py
visma/gui/__init__.py
visma/gui/cli.py
visma/gui/logger.py
visma/gui/plotter.py
visma/gui/qsolver.py
visma/gui/settings.py
visma/gui/steps.py
visma/gui/window.py
visma/io/__init__.py
visma/io/checks.py
visma/io/parser.py
visma/io/tokenize.py
visma/matrix/__init__.py
visma/matrix/checks.py
visma/matrix/operations.py
visma/matrix/special.py
visma/matrix/structure.py
visma/simplify/__init__.py
visma/simplify/addsub.py
visma/simplify/muldiv.py
visma/simplify/simplify.py
visma/solvers/__init__.py
visma/solvers/simulEqn.py
visma/solvers/solve.py
visma/solvers/polynomial/__init__.py
visma/solvers/polynomial/cubic.py
visma/solvers/polynomial/quadratic.py
visma/solvers/polynomial/quartic.py
visma/solvers/polynomial/roots.py
visma/testbed/__init__.py
visma/testbed/graph.py
visma/testbed/id.py
visma/transform/__init__.py
visma/transform/factorization.py
visma/transform/substitution.py
visma/utils/__init__.py
visma/utils/integers.py
visma/utils/polynomials.py
VISualMAth-1.0.0.0.dist-info/LICENSE
VISualMAth-1.0.0.0.dist-info/METADATA
VISualMAth-1.0.0.0.dist-info/WHEEL
VISualMAth-1.0.0.0.dist-info/top_level.txt
VISualMAth-1.0.0.0.dist-info/RECORD
