Metadata-Version: 2.1
Name: VISualMAth
Version: 1.0.0.0
Summary: visma - VISual MAth : A math equation solver and visualizer
Home-page: https://github.com/aerospaceresearch/visma
Author: Siddharth Kothiyal, Shantanu Mishra, Mayank Dhiman
Author-email: sid.kothiyal27@gmail.com, 8hantanu@gmail.com, mdhiman536@gmail.com
License: UNKNOWN
Project-URL: Documentation, https://github.com/aerospaceresearch/visma/wiki
Project-URL: Source, https://github.com/aerospaceresearch/visma
Project-URL: Issues, https://github.com/aerospaceresearch/visma/issues
Project-URL: Chat, https://gitter.im/aerospaceresearch/visma
Platform: UNKNOWN
Classifier: Programming Language :: Python :: 3
Classifier: Programming Language :: Python :: 3.4
Classifier: Programming Language :: Python :: 3.5
Classifier: Programming Language :: Python :: 3.6
Classifier: Programming Language :: Python :: 3.7
Classifier: Operating System :: OS Independent
Classifier: Topic :: Scientific/Engineering
Classifier: Topic :: Scientific/Engineering :: Mathematics
Classifier: Topic :: Scientific/Engineering :: Visualization
Classifier: License :: OSI Approved :: GNU General Public License v3 (GPLv3)
Requires-Python: >=3
Requires-Dist: PyQt5
Requires-Dist: matplotlib
Requires-Dist: numpy
